dist
docs
examples
opof_grid2d
tests
