Metadata-Version: 2.1
Name: opof-grid2d
Version: 0.2.0
Summary: OPOF domains for 2D grid worlds
Home-page: https://github.com/opoframework/opof-grid2d
Author: Yiyuan Lee
Author-email: yiyuan.lee@rice.edu
License: BSD-3
Project-URL: Source, https://github.com/opoframework/opof-grid2d
Keywords: opof,optimization,machine learning,reinforcement learning,planning,grid world,robotics
Classifier: Development Status :: 4 - Beta
Classifier: Intended Audience :: Developers
Classifier: Intended Audience :: Education
Classifier: Intended Audience :: Science/Research
Classifier: Topic :: Scientific/Engineering
Classifier: Topic :: Scientific/Engineering :: Mathematics
Classifier: Topic :: Scientific/Engineering :: Artificial Intelligence
Classifier: Topic :: Software Development
Classifier: Topic :: Software Development :: Libraries
Classifier: Topic :: Software Development :: Libraries :: Python Modules
Classifier: License :: OSI Approved :: BSD License
Classifier: Programming Language :: Python :: 3.9
Classifier: Programming Language :: Python :: 3.10
Classifier: Programming Language :: Python :: 3.11
Requires-Python: >=3.9
License-File: LICENSE.md
Requires-Dist: opof
Requires-Dist: torch
Requires-Dist: numpy
Requires-Dist: sortedcontainers
Requires-Dist: tqdm
Requires-Dist: mazelib-alt
Provides-Extra: tests
Requires-Dist: pytest ; extra == 'tests'
Requires-Dist: pytest-cov ; extra == 'tests'
Requires-Dist: pytest-timeout ; extra == 'tests'
